featureform/__init__.py
featureform/__main__.py
featureform/cli.py
featureform/client.py
featureform/constants.py
featureform/deploy.py
featureform/enums.py
featureform/exceptions.py
featureform/feature_flag.py
featureform/features.py
featureform/file_utils.py
featureform/format.py
featureform/get.py
featureform/grpc_client.py
featureform/list.py
featureform/logging.py
featureform/parse.py
featureform/register.py
featureform/resources.py
featureform/search.py
featureform/secret_provider.py
featureform/serving.py
featureform/status_display.py
featureform/tls.py
featureform/train_test_split.py
featureform/type_objects.py
featureform/types.py
featureform/utils.py
featureform/variant_names_generator.py
featureform/version.py
featureform/lib/__init__.py
featureform/lib/auth.py
featureform/proto/metadata.proto
featureform/proto/metadata_pb2.py
featureform/proto/metadata_pb2.pyi
featureform/proto/metadata_pb2_grpc.py
featureform/proto/serving.proto
featureform/proto/serving_pb2.py
featureform/proto/serving_pb2.pyi
featureform/proto/serving_pb2_grpc.py
featureform_enterprise-0.16.11.dist-info/licenses/LICENSE
featureform_enterprise-0.16.11.dist-info/METADATA
featureform_enterprise-0.16.11.dist-info/WHEEL
featureform_enterprise-0.16.11.dist-info/entry_points.txt
featureform_enterprise-0.16.11.dist-info/top_level.txt
featureform_enterprise-0.16.11.dist-info/RECORD
